{
	"parent": "item/handheld",
	"textures": {
		"layer0": "item/carrot_on_a_stick"
	},
	"overrides": [
		{ "predicate": { "custom_model_data": 1}, "model": "item/carrot_on_a_stick/1" },
		{ "predicate": { "custom_model_data": 2}, "model": "item/carrot_on_a_stick/2" },
		{ "predicate": { "custom_model_data": 3}, "model": "item/carrot_on_a_stick/3" },
		{ "predicate": { "custom_model_data": 4}, "model": "item/carrot_on_a_stick/4" },
		{ "predicate": { "custom_model_data": 5}, "model": "item/carrot_on_a_stick/5" },
		{ "predicate": { "custom_model_data": 6}, "model": "item/carrot_on_a_stick/6" },
		{ "predicate": { "custom_model_data": 7}, "model": "item/carrot_on_a_stick/7" },
		{ "predicate": { "custom_model_data": 8}, "model": "item/carrot_on_a_stick/8" },
		{ "predicate": { "custom_model_data": 11}, "model": "item/carrot_on_a_stick/11" },
		{ "predicate": { "custom_model_data": 12}, "model": "item/carrot_on_a_stick/12" },
		{ "predicate": { "custom_model_data": 13}, "model": "item/carrot_on_a_stick/13" },
		{ "predicate": { "custom_model_data": 14}, "model": "item/carrot_on_a_stick/14" },
		{ "predicate": { "custom_model_data": 15}, "model": "item/carrot_on_a_stick/15" },
		{ "predicate": { "custom_model_data": 16}, "model": "item/carrot_on_a_stick/16" },
		{ "predicate": { "custom_model_data": 17}, "model": "item/carrot_on_a_stick/17" },
		{ "predicate": { "custom_model_data": 18}, "model": "item/carrot_on_a_stick/18" },
		{ "predicate": { "custom_model_data": 21}, "model": "item/carrot_on_a_stick/21" },
		{ "predicate": { "custom_model_data": 22}, "model": "item/carrot_on_a_stick/22" },
		{ "predicate": { "custom_model_data": 23}, "model": "item/carrot_on_a_stick/23" },
		{ "predicate": { "custom_model_data": 24}, "model": "item/carrot_on_a_stick/24" },
		{ "predicate": { "custom_model_data": 25}, "model": "item/carrot_on_a_stick/25" },
		{ "predicate": { "custom_model_data": 26}, "model": "item/carrot_on_a_stick/26" },
		{ "predicate": { "custom_model_data": 27}, "model": "item/carrot_on_a_stick/27" },
		{ "predicate": { "custom_model_data": 28}, "model": "item/carrot_on_a_stick/28" },
		{ "predicate": { "custom_model_data": 31}, "model": "item/carrot_on_a_stick/31" },
		{ "predicate": { "custom_model_data": 32}, "model": "item/carrot_on_a_stick/32" },
		{ "predicate": { "custom_model_data": 33}, "model": "item/carrot_on_a_stick/33" },
		{ "predicate": { "custom_model_data": 34}, "model": "item/carrot_on_a_stick/34" },
		{ "predicate": { "custom_model_data": 35}, "model": "item/carrot_on_a_stick/35" },
		{ "predicate": { "custom_model_data": 36}, "model": "item/carrot_on_a_stick/36" },
		{ "predicate": { "custom_model_data": 37}, "model": "item/carrot_on_a_stick/37" },
		{ "predicate": { "custom_model_data": 38}, "model": "item/carrot_on_a_stick/38" },
		{ "predicate": { "custom_model_data": 41}, "model": "item/carrot_on_a_stick/41" },
		{ "predicate": { "custom_model_data": 42}, "model": "item/carrot_on_a_stick/42" },
		{ "predicate": { "custom_model_data": 43}, "model": "item/carrot_on_a_stick/43" },
		{ "predicate": { "custom_model_data": 44}, "model": "item/carrot_on_a_stick/44" },
		{ "predicate": { "custom_model_data": 45}, "model": "item/carrot_on_a_stick/45" },
		{ "predicate": { "custom_model_data": 46}, "model": "item/carrot_on_a_stick/46" },
		{ "predicate": { "custom_model_data": 47}, "model": "item/carrot_on_a_stick/47" },
		{ "predicate": { "custom_model_data": 48}, "model": "item/carrot_on_a_stick/48" },
		{ "predicate": { "custom_model_data": 51}, "model": "item/carrot_on_a_stick/51" },
		{ "predicate": { "custom_model_data": 52}, "model": "item/carrot_on_a_stick/52" },
		{ "predicate": { "custom_model_data": 53}, "model": "item/carrot_on_a_stick/53" },
		{ "predicate": { "custom_model_data": 54}, "model": "item/carrot_on_a_stick/54" },
		{ "predicate": { "custom_model_data": 55}, "model": "item/carrot_on_a_stick/55" },
		{ "predicate": { "custom_model_data": 56}, "model": "item/carrot_on_a_stick/56" },
		{ "predicate": { "custom_model_data": 57}, "model": "item/carrot_on_a_stick/57" },
		{ "predicate": { "custom_model_data": 58}, "model": "item/carrot_on_a_stick/58" },
		{ "predicate": { "custom_model_data": 61}, "model": "item/carrot_on_a_stick/61" },
		{ "predicate": { "custom_model_data": 62}, "model": "item/carrot_on_a_stick/62" },
		{ "predicate": { "custom_model_data": 63}, "model": "item/carrot_on_a_stick/63" },
		{ "predicate": { "custom_model_data": 64}, "model": "item/carrot_on_a_stick/64" },
		{ "predicate": { "custom_model_data": 65}, "model": "item/carrot_on_a_stick/65" },
		{ "predicate": { "custom_model_data": 66}, "model": "item/carrot_on_a_stick/66" },
		{ "predicate": { "custom_model_data": 67}, "model": "item/carrot_on_a_stick/67" },
		{ "predicate": { "custom_model_data": 68}, "model": "item/carrot_on_a_stick/68" },
		{ "predicate": { "custom_model_data": 71}, "model": "item/carrot_on_a_stick/71" },
		{ "predicate": { "custom_model_data": 72}, "model": "item/carrot_on_a_stick/72" },
		{ "predicate": { "custom_model_data": 73}, "model": "item/carrot_on_a_stick/73" },
		{ "predicate": { "custom_model_data": 74}, "model": "item/carrot_on_a_stick/74" },
		{ "predicate": { "custom_model_data": 75}, "model": "item/carrot_on_a_stick/75" },
		{ "predicate": { "custom_model_data": 76}, "model": "item/carrot_on_a_stick/76" },
		{ "predicate": { "custom_model_data": 77}, "model": "item/carrot_on_a_stick/77" },
		{ "predicate": { "custom_model_data": 78}, "model": "item/carrot_on_a_stick/78" },
		{ "predicate": { "custom_model_data": 81}, "model": "item/carrot_on_a_stick/81" },
		{ "predicate": { "custom_model_data": 82}, "model": "item/carrot_on_a_stick/82" },
		{ "predicate": { "custom_model_data": 83}, "model": "item/carrot_on_a_stick/83" },
		{ "predicate": { "custom_model_data": 84}, "model": "item/carrot_on_a_stick/84" },
		{ "predicate": { "custom_model_data": 85}, "model": "item/carrot_on_a_stick/85" },
		{ "predicate": { "custom_model_data": 86}, "model": "item/carrot_on_a_stick/86" },
		{ "predicate": { "custom_model_data": 87}, "model": "item/carrot_on_a_stick/87" },
		{ "predicate": { "custom_model_data": 88}, "model": "item/carrot_on_a_stick/88" },
		{ "predicate": { "custom_model_data": 91}, "model": "item/carrot_on_a_stick/91" },
		{ "predicate": { "custom_model_data": 92}, "model": "item/carrot_on_a_stick/92" },
		{ "predicate": { "custom_model_data": 93}, "model": "item/carrot_on_a_stick/93" },
		{ "predicate": { "custom_model_data": 94}, "model": "item/carrot_on_a_stick/94" },
		{ "predicate": { "custom_model_data": 95}, "model": "item/carrot_on_a_stick/95" },
		{ "predicate": { "custom_model_data": 96}, "model": "item/carrot_on_a_stick/96" },
		{ "predicate": { "custom_model_data": 97}, "model": "item/carrot_on_a_stick/97" },
		{ "predicate": { "custom_model_data": 98}, "model": "item/carrot_on_a_stick/98" },
		{ "predicate": { "custom_model_data": 101}, "model": "item/carrot_on_a_stick/101" },
		{ "predicate": { "custom_model_data": 102}, "model": "item/carrot_on_a_stick/102" },
		{ "predicate": { "custom_model_data": 103}, "model": "item/carrot_on_a_stick/103" },
		{ "predicate": { "custom_model_data": 104}, "model": "item/carrot_on_a_stick/104" },
		{ "predicate": { "custom_model_data": 105}, "model": "item/carrot_on_a_stick/105" },
		{ "predicate": { "custom_model_data": 106}, "model": "item/carrot_on_a_stick/106" },
		{ "predicate": { "custom_model_data": 107}, "model": "item/carrot_on_a_stick/107" },
		{ "predicate": { "custom_model_data": 108}, "model": "item/carrot_on_a_stick/108" },
		{ "predicate": { "custom_model_data": 111}, "model": "item/carrot_on_a_stick/111" },
		{ "predicate": { "custom_model_data": 112}, "model": "item/carrot_on_a_stick/112" },
		{ "predicate": { "custom_model_data": 113}, "model": "item/carrot_on_a_stick/113" },
		{ "predicate": { "custom_model_data": 114}, "model": "item/carrot_on_a_stick/114" },
		{ "predicate": { "custom_model_data": 115}, "model": "item/carrot_on_a_stick/115" },
		{ "predicate": { "custom_model_data": 116}, "model": "item/carrot_on_a_stick/116" },
		{ "predicate": { "custom_model_data": 117}, "model": "item/carrot_on_a_stick/117" },
		{ "predicate": { "custom_model_data": 118}, "model": "item/carrot_on_a_stick/118" }
	]
}
